encryptor/__init__.py
encryptor/__version__.py
encryptor/curves.py
encryptor/encrypt.py
encryptor/entry_points.py
villa_encryptor_thanakijwanavit-0.0.11.dist-info/LICENSE
villa_encryptor_thanakijwanavit-0.0.11.dist-info/METADATA
villa_encryptor_thanakijwanavit-0.0.11.dist-info/WHEEL
villa_encryptor_thanakijwanavit-0.0.11.dist-info/entry_points.txt
villa_encryptor_thanakijwanavit-0.0.11.dist-info/top_level.txt
villa_encryptor_thanakijwanavit-0.0.11.dist-info/RECORD
