Metadata-Version: 2.1
Name: villa-encryptor-thanakijwanavit
Version: 0.0.11
Summary: encrypt and decrypt data based on villa api
Home-page: https://github.com/thanakijwanavit/villaWallet
Author: Nic Wanavit
Author-email: nwanavit@hatari.cc
License: Apache 2.0
Keywords: villa encryption
Platform: UNKNOWN
Classifier: Development Status :: 4 - Beta
Classifier: Intended Audience :: Developers
Classifier: Programming Language :: Python :: 3.8
Requires-Python: >=3.6.*
Requires-Dist: numpy
Requires-Dist: requests
Requires-Dist: boto3
